missingbuiltins/__init__.py
missingbuiltins-0.0.2.dist-info/AUTHORS.rst
missingbuiltins-0.0.2.dist-info/LICENSE
missingbuiltins-0.0.2.dist-info/METADATA
missingbuiltins-0.0.2.dist-info/WHEEL
missingbuiltins-0.0.2.dist-info/top_level.txt
missingbuiltins-0.0.2.dist-info/RECORD
