Metadata-Version: 2.1
Name: missingbuiltins
Version: 0.0.2
Summary: Code I write over and over for no good reason
Home-page: https://github.com/jbn/missingbuiltins
Author: John Bjorn Nelson
Author-email: jbn@abreka.com
License: GNU General Public License v3
Keywords: missingbuiltins
Platform: UNKNOWN
Classifier: Development Status :: 2 - Pre-Alpha
Classifier: Intended Audience :: Developers
Classifier: License :: OSI Approved :: GNU General Public License v3 (GPLv3)
Classifier: Natural Language :: English
Classifier: Programming Language :: Python :: 3
Classifier: Programming Language :: Python :: 3.5
Classifier: Programming Language :: Python :: 3.6
Classifier: Programming Language :: Python :: 3.7
Classifier: Programming Language :: Python :: 3.8
Requires-Python: >=3.5
